mastercard_api_core-1.4.12.dist-info/DESCRIPTION.rst
mastercard_api_core-1.4.12.dist-info/METADATA
mastercard_api_core-1.4.12.dist-info/RECORD
mastercard_api_core-1.4.12.dist-info/WHEEL
mastercard_api_core-1.4.12.dist-info/metadata.json
mastercard_api_core-1.4.12.dist-info/top_level.txt
mastercardapicore/__init__.py
mastercardapicore/version.py
mastercardapicore/core/__init__.py
mastercardapicore/core/baseobject.py
mastercardapicore/core/config.py
mastercardapicore/core/constants.py
mastercardapicore/core/controller.py
mastercardapicore/core/exceptions.py
mastercardapicore/core/model.py
mastercardapicore/core/util.py
mastercardapicore/security/__init__.py
mastercardapicore/security/authentication.py
mastercardapicore/security/oauth.py
mastercardapicore/security/util.py
tests/__init__.py
tests/api/__init__.py
tests/api/accountinquiry.py
tests/api/base_test.py
tests/api/combinationctrlsalertresource.py
tests/api/echo.py
tests/api/insights.py
tests/api/multiplepathuserpost.py
tests/api/test_accountinquiry.py
tests/api/test_echo.py
tests/api/test_insights.py
tests/api/test_multiplepathuserpost.py
tests/api/test_spendcontrols.py
tests/api/test_user.py
tests/api/test_userpostheader.py
tests/api/test_userpostpath.py
tests/api/user.py
tests/api/userpostheader.py
tests/api/userpostpath.py
tests/core/__init__.py
tests/core/test_controller.py
tests/core/test_model.py
tests/core/test_resourceconfig.py
tests/core/test_util.py
tests/resources/__init__.py
tests/security/__init__.py
tests/security/test_oauth.py
