Metadata-Version: 2.0
Name: mastercard-api-core
Version: 1.4.12
Summary: MasterCard API Python Core SDK
Home-page: https://www.developer.mastercard.com
Author: MasterCard Worldwide
Author-email: APISupport@mastercard.com
License: BSD2
Platform: UNKNOWN
Classifier: Intended Audience :: Developers
Classifier: Natural Language :: English
Classifier: Operating System :: OS Independent
Classifier: Programming Language :: Python :: 2.7
Classifier: Programming Language :: Python :: 3.5
Classifier: Programming Language :: Python :: 3.6
Classifier: Topic :: Software Development :: Libraries :: Python Modules
Requires-Dist: requests
Requires-Dist: pyOpenSSL
Requires-Dist: urllib3[secure]
Requires-Dist: cryptography
Requires-Dist: future
